command_streamer/__init__.py
command_streamer/tests.py
command_streamer-0.0.3.dist-info/DESCRIPTION.rst
command_streamer-0.0.3.dist-info/METADATA
command_streamer-0.0.3.dist-info/RECORD
command_streamer-0.0.3.dist-info/WHEEL
command_streamer-0.0.3.dist-info/metadata.json
command_streamer-0.0.3.dist-info/top_level.txt
